{"SubTexture":[{"width":75,"y":266,"height":40,"name":"weapon_1005_folder/weapon_r_0","x":111},{"frameHeight":37,"y":270,"frameX":0,"width":81,"frameY":0,"height":36,"name":"weapon_1005_folder/a_folder/boss_zhl.0002","frameWidth":81,"x":1},{"frameHeight":37,"y":237,"frameX":0,"width":81,"frameY":0,"height":36,"name":"weapon_1005_folder/a_folder/boss_zhl.0003","frameWidth":81,"x":277},{"width":81,"y":237,"height":37,"name":"weapon_1005_folder/a_folder/boss_zhl.0001","x":194},{"width":81,"y":227,"height":37,"name":"weapon_1005_folder/a_folder/boss_zhl.0005","x":111},{"width":81,"y":72,"height":37,"name":"weapon_1005_folder/a_folder/boss_zhl.0004","x":421},{"width":105,"y":128,"height":60,"name":"weapon_1005_folder/weapon_r_1","x":387},{"width":110,"y":178,"height":47,"name":"weapon_1005_folder/b_folder/0","x":1},{"width":108,"y":227,"height":41,"name":"weapon_1005_folder/b_folder/3","x":1},{"width":108,"y":180,"height":45,"name":"weapon_1005_folder/b_folder/2","x":113},{"width":108,"y":194,"height":41,"name":"weapon_1005_folder/b_folder/4","x":223},{"width":109,"y":190,"height":49,"name":"weapon_1005_folder/b_folder/1","x":387},{"width":108,"y":128,"height":64,"name":"weapon_1005_folder/weapon_r_2","x":277},{"width":136,"y":72,"height":54,"name":"weapon_1005_folder/c_folder/1","x":283},{"width":136,"y":132,"height":46,"name":"weapon_1005_folder/c_folder/4","x":139},{"width":136,"y":133,"height":43,"name":"weapon_1005_folder/c_folder/3","x":1},{"width":136,"y":79,"height":52,"name":"weapon_1005_folder/c_folder/0","x":1},{"width":136,"y":79,"height":51,"name":"weapon_1005_folder/c_folder/2","x":139},{"width":202,"y":1,"height":69,"name":"weapon_1005_folder/weapon_r_3","x":283},{"width":280,"y":1,"height":76,"name":"weapon_1005_folder/weapon_r_4","x":1}],"name":"weapon_1000","imagePath":"weapon_1000_tex.png"}